KratosMultiphysics/ShallowWaterApplication/__init__.py
KratosMultiphysics/ShallowWaterApplication/apply_absorbing_boundary_process.py
KratosMultiphysics/ShallowWaterApplication/apply_slip_process.py
KratosMultiphysics/ShallowWaterApplication/automatic_dirichlet_conditions_process.py
KratosMultiphysics/ShallowWaterApplication/boussinesq_solver.py
KratosMultiphysics/ShallowWaterApplication/derivatives_recovery_process.py
KratosMultiphysics/ShallowWaterApplication/lagrangian_shallow_water_solver.py
KratosMultiphysics/ShallowWaterApplication/primitive_solver.py
KratosMultiphysics/ShallowWaterApplication/set_initial_perturbation_process.py
KratosMultiphysics/ShallowWaterApplication/set_initial_water_level_process.py
KratosMultiphysics/ShallowWaterApplication/set_topography_process.py
KratosMultiphysics/ShallowWaterApplication/shallow_water_analysis.py
KratosMultiphysics/ShallowWaterApplication/shallow_water_base_solver.py
KratosMultiphysics/ShallowWaterApplication/stabilized_shallow_water_solver.py
KratosMultiphysics/ShallowWaterApplication/wave_generator_process.py
KratosMultiphysics/ShallowWaterApplication/wave_solver.py
KratosMultiphysics/ShallowWaterApplication/benchmarks/base_benchmark_process.py
KratosMultiphysics/ShallowWaterApplication/benchmarks/dam_break_benchmark.py
KratosMultiphysics/ShallowWaterApplication/benchmarks/mac_donald_shock_benchmark.py
KratosMultiphysics/ShallowWaterApplication/benchmarks/mac_donald_transition_benchmark.py
KratosMultiphysics/ShallowWaterApplication/benchmarks/planar_surface_in_parabola_benchmark.py
KratosMultiphysics/ShallowWaterApplication/benchmarks/solitary_wave_benchmark.py
KratosMultiphysics/ShallowWaterApplication/coupling/compute_boundary_force_process.py
KratosMultiphysics/ShallowWaterApplication/coupling/depth_integration_input_process.py
KratosMultiphysics/ShallowWaterApplication/coupling/depth_integration_output_process.py
KratosMultiphysics/ShallowWaterApplication/coupling/read_from_sw_interface_process.py
kratosshallowwaterapplication-10.4.0.dist-info/METADATA
kratosshallowwaterapplication-10.4.0.dist-info/WHEEL
kratosshallowwaterapplication-10.4.0.dist-info/RECORD
